PyNormaliz_inequalities/__init__.py
PyNormaliz_inequalities/inequalities.py
PyNormaliz_inequalities-0.1.2.dist-info/LICENSE
PyNormaliz_inequalities-0.1.2.dist-info/METADATA
PyNormaliz_inequalities-0.1.2.dist-info/WHEEL
PyNormaliz_inequalities-0.1.2.dist-info/top_level.txt
PyNormaliz_inequalities-0.1.2.dist-info/RECORD
