Metadata-Version: 2.1
Name: PyNormaliz_inequalities
Version: 0.1.2
Summary: A Python package for interacting with PyNormaliz using inequalities.
Author-email: Dominik Peters <mail@dominik-peters.de>
License: MIT License
Project-URL: Homepage, https://github.com/DominikPeters/PyNormaliz_inequalities
Project-URL: Issues, https://github.com/DominikPeters/PyNormaliz_inequalities/issues
License-File: LICENSE
Requires-Dist: PyNormaliz
